MANIFEST.in
README.md
setup.py
pokemontools/__init__.py
pokemontools/addresses.py
pokemontools/baserom.gbc
pokemontools/chars.py
pokemontools/comparator.py
pokemontools/configuration.py
pokemontools/crystal.py
pokemontools/disassemble_map_scripts.py
pokemontools/dump_sections.py
pokemontools/exceptions.py
pokemontools/gbhw.asm
pokemontools/gbz80disasm.py
pokemontools/gfx.py
pokemontools/graph.py
pokemontools/helpers.py
pokemontools/hram.asm
pokemontools/interval_map.py
pokemontools/item_constants.py
pokemontools/labels.json
pokemontools/labels.py
pokemontools/map_editor.py
pokemontools/map_names.py
pokemontools/move_constants.py
pokemontools/old_parse_scripts.py
pokemontools/old_text_script.py
pokemontools/overworldripper.py
pokemontools/parse_consecutive_strings.py
pokemontools/pksv.py
pokemontools/pointers.py
pokemontools/pokemon_constants.py
pokemontools/preprocessor.py
pokemontools/redmusicdisasm.py
pokemontools/redsfxdisasm.py
pokemontools/redsfxheaders.py
pokemontools/romstr.py
pokemontools/sym.py
pokemontools/trainers.py
pokemontools/type_constants.py
pokemontools/wram.asm
pokemontools/wram.py
pokemontools.egg-info/PKG-INFO
pokemontools.egg-info/SOURCES.txt
pokemontools.egg-info/dependency_links.txt
pokemontools.egg-info/requires.txt
pokemontools.egg-info/top_level.txt
pokemontools/crystalparts/__init__.py
pokemontools/crystalparts/asmline.py
pokemontools/crystalparts/old_parsers.py
pokemontools/vba/__init__.py
pokemontools/vba/autoplayer.py
pokemontools/vba/baserom.gbc
pokemontools/vba/battle.py
pokemontools/vba/keyboard.data
pokemontools/vba/keyboard.py
pokemontools/vba/vba.py
redtools/__init__.py
redtools/add_map_labels_to_map_headers.py
redtools/analyze_incbins.py
redtools/analyze_texts.py
redtools/connection_helper.py
redtools/extract_maps.py
redtools/extract_tileblocks.py
redtools/extract_tilesets.py
redtools/fix_labels.py
redtools/gbz80disasm.py
redtools/generate_sys.py
redtools/insert_object_data.py
redtools/insert_texts.py
redtools/make_map_size_constants.py
redtools/map_block_dumper.py
redtools/pokered_dir.py
redtools/pretty_map_headers.py
redtools/pretty_text.py
redtools/pretty_trainer_headers.py
