Metadata-Version: 1.1
Name: pokemontools
Version: 1.6.0
Summary: Tools for compiling and disassembling Pokémon Red and Pokémon Crystal.
Home-page: https://github.com/kanzure/pokemon-reverse-engineering-tools
Author: Bryan Bishop
Author-email: kanzure@gmail.com
License: BSD
Platform: any
Classifier: License :: OSI Approved :: BSD License
Classifier: Operating System :: OS Independent
Classifier: Topic :: Software Development :: Libraries :: Python Modules
Classifier: Programming Language :: Python
Classifier: Programming Language :: Python :: 2.7
